taxbrain/__init__.py
taxbrain/cli.py
taxbrain/conftest.py
taxbrain/corporate_incidence.py
taxbrain/report.py
taxbrain/report_utils.py
taxbrain/taxbrain.py
taxbrain/typing.py
taxbrain/utils.py
taxbrain/report_files/report_style.css
taxbrain/report_files/report_template.md
taxbrain/report_files/taxbrain.png
taxbrain/tests/conftest.py
taxbrain/tests/expected_weighted_table.csv
taxbrain/tests/test_brain.py
taxbrain/tests/test_cli.py
taxbrain/tests/test_corporate_incidence.py
taxbrain/tests/test_report.py
taxbrain/tests/test_utils.py
taxbrain-2.7.2.dist-info/LICENSE.md
taxbrain-2.7.2.dist-info/METADATA
taxbrain-2.7.2.dist-info/WHEEL
taxbrain-2.7.2.dist-info/entry_points.txt
taxbrain-2.7.2.dist-info/top_level.txt
taxbrain-2.7.2.dist-info/RECORD
