Metadata-Version: 2.1
Name: taxbrain
Version: 2.7.2
Summary: Python library for advanced tax policy analysis
Home-page: https://github.com/PSLmodels/Tax-Brain
Author: Anderson Frailey
Author-email: andersonfrailey@gmail.com
License: MIT
Classifier: Programming Language :: Python :: 3
Classifier: Programming Language :: Python :: 3.10
Classifier: Programming Language :: Python :: 3.11
Classifier: Programming Language :: Python :: 3.12
Classifier: License :: OSI Approved :: MIT License
Classifier: Operating System :: OS Independent
License-File: LICENSE.md
Requires-Dist: taxcalc
Requires-Dist: behresp
Requires-Dist: dask
Requires-Dist: bokeh
